{
 "actions": [],
 "allow_rename": 1,
 "creation": "2025-12-04 12:00:00.000000",
 "doctype": "DocType",
 "editable_grid": 1,
 "engine": "InnoDB",
 "field_order": [
  "sample_id",
  "sample_time",
  "status",
  "overall_result",
  "column_break_header",
  "spec_master",
  "lab_technician",
  "section_legacy_elements",
  "si_percent",
  "fe_percent",
  "cu_percent",
  "mn_percent",
  "column_break_elements2",
  "mg_percent",
  "zn_percent",
  "ti_percent",
  "al_percent",
  "section_element_results",
  "elements",
  "section_notes",
  "result_status",
  "correction_required",
  "correction_note",
  "remarks",
  "section_qc_feedback",
  "qc_status",
  "qc_comment",
  "qc_deviation_summary",
  "qc_deviation_count",
  "qc_deviation_detail",
  "qc_last_updated_by",
  "qc_last_updated_on"
 ],
 "fields": [
  {
   "fieldname": "sample_id",
   "fieldtype": "Data",
   "in_list_view": 1,
   "label": "Sample ID",
   "reqd": 1
  },
  {
   "fieldname": "sample_time",
   "fieldtype": "Datetime",
   "in_list_view": 1,
   "label": "Sample Time"
  },
  {
   "default": "Pending",
   "fieldname": "status",
   "fieldtype": "Select",
   "in_list_view": 1,
   "label": "Status",
   "options": "Pending\nIn Lab\nAccepted\nRejected\nCorrection Required"
  },
  {
   "default": "Pending",
   "fieldname": "overall_result",
   "fieldtype": "Select",
   "in_list_view": 1,
   "label": "Overall Result",
   "options": "Pending\nIn Spec\nOut of Spec"
  },
  {
   "fieldname": "column_break_header",
   "fieldtype": "Column Break"
  },
  {
   "description": "Active Alloy Chemical Composition Master used for this sample",
   "fieldname": "spec_master",
   "fieldtype": "Link",
   "label": "Composition Master",
   "options": "Alloy Chemical Composition Master"
  },
  {
   "fieldname": "lab_technician",
   "fieldtype": "Link",
   "label": "Lab Technician",
   "options": "User"
  },
  {
   "collapsible": 1,
   "collapsible_depends_on": "eval:doc.elements && doc.elements.length > 0",
   "description": "Legacy element fields for backward compatibility",
   "fieldname": "section_legacy_elements",
   "fieldtype": "Section Break",
   "label": "Quick Entry (Legacy)"
  },
  {
   "fieldname": "si_percent",
   "fieldtype": "Float",
   "label": "Si %",
   "precision": "4"
  },
  {
   "fieldname": "fe_percent",
   "fieldtype": "Float",
   "label": "Fe %",
   "precision": "4"
  },
  {
   "fieldname": "cu_percent",
   "fieldtype": "Float",
   "label": "Cu %",
   "precision": "4"
  },
  {
   "fieldname": "mn_percent",
   "fieldtype": "Float",
   "label": "Mn %",
   "precision": "4"
  },
  {
   "fieldname": "column_break_elements2",
   "fieldtype": "Column Break"
  },
  {
   "fieldname": "mg_percent",
   "fieldtype": "Float",
   "label": "Mg %",
   "precision": "4"
  },
  {
   "fieldname": "zn_percent",
   "fieldtype": "Float",
   "label": "Zn %",
   "precision": "4"
  },
  {
   "fieldname": "ti_percent",
   "fieldtype": "Float",
   "label": "Ti %",
   "precision": "4"
  },
  {
   "fieldname": "al_percent",
   "fieldtype": "Float",
   "label": "Al %",
   "precision": "4"
  },
  {
   "description": "Detailed element results from QC evaluation",
   "fieldname": "section_element_results",
   "fieldtype": "Section Break",
   "label": "Element Results"
  },
  {
   "fieldname": "elements",
   "fieldtype": "Table",
   "label": "Element Results",
   "options": "Melting Sample Element Result"
  },
  {
   "fieldname": "section_notes",
   "fieldtype": "Section Break",
   "label": "Notes & Status"
  },
  {
   "default": "Pending",
   "description": "Legacy status field",
   "fieldname": "result_status",
   "fieldtype": "Select",
   "hidden": 1,
   "label": "Result Status (Legacy)",
   "options": "Pending\nWithin Limit\nOut of Limit"
  },
  {
   "default": "0",
   "fieldname": "correction_required",
   "fieldtype": "Check",
   "label": "Correction Required"
  },
  {
   "depends_on": "eval:doc.correction_required || doc.status == 'Correction Required'",
   "fieldname": "correction_note",
   "fieldtype": "Small Text",
   "label": "Correction Note"
  },
  {
   "fieldname": "remarks",
   "fieldtype": "Small Text",
   "label": "Remarks"
  },
  {
   "collapsible": 1,
   "fieldname": "section_qc_feedback",
   "fieldtype": "Section Break",
   "label": "QC Feedback"
  },
  {
   "default": "Pending",
   "fieldname": "qc_status",
   "fieldtype": "Select",
   "label": "QC Status",
   "options": "Pending\nWithin Spec\nOut of Spec\nCorrection Required\nRejected"
  },
  {
   "fieldname": "qc_comment",
   "fieldtype": "Small Text",
   "label": "QC Comment"
  },
  {
   "fieldname": "qc_deviation_summary",
   "fieldtype": "Long Text",
   "label": "QC Deviation Summary"
  },
  {
   "default": "0",
   "fieldname": "qc_deviation_count",
   "fieldtype": "Int",
   "label": "QC Deviation Count"
  },
  {
   "fieldname": "qc_deviation_detail",
   "fieldtype": "Long Text",
   "label": "QC Deviation Detail (JSON)"
  },
  {
   "fieldname": "qc_last_updated_by",
   "fieldtype": "Data",
   "label": "QC Last Updated By"
  },
  {
   "fieldname": "qc_last_updated_on",
   "fieldtype": "Datetime",
   "label": "QC Last Updated On"
  }
 ],
 "index_web_pages_for_search": 1,
 "istable": 1,
 "links": [],
 "modified": "2025-12-05 12:00:00.000000",
 "modified_by": "Administrator",
 "module": "Swynix MES",
 "name": "Melting Batch Spectro Sample",
 "owner": "Administrator",
 "permissions": [],
 "sort_field": "modified",
 "sort_order": "DESC",
 "states": []
}
